pandas_ylt/__init__.py
pandas_ylt/base_classes.py
pandas_ylt/eventlossbeta.py
pandas_ylt/layer.py
pandas_ylt/lossexceedance.py
pandas_ylt/yeareventallocloss.py
pandas_ylt/yeareventloss.py
pandas_ylt/yearloss.py
pandas_ylt-0.2.0.dist-info/licenses/LICENSE
pandas_ylt-0.2.0.dist-info/METADATA
pandas_ylt-0.2.0.dist-info/WHEEL
pandas_ylt-0.2.0.dist-info/top_level.txt
pandas_ylt-0.2.0.dist-info/RECORD
