Metadata-Version: 2.4
Name: pandas-ylt
Version: 0.2.0
Summary: Wrappers to help work with Year Loss Table data in python pandas
Author: Iain Bailey
License: MIT License
Project-URL: Homepage, https://github.com/iwbailey/pandas-ylt
Classifier: Programming Language :: Python :: 3
Classifier: License :: OSI Approved :: MIT License
Classifier: Operating System :: OS Independent
Requires-Python: >=3.7
License-File: LICENSE
Requires-Dist: pandas>=2.2
Requires-Dist: numpy>=2.1
Requires-Dist: scipy>=1.14
Provides-Extra: dev
Requires-Dist: matplotlib>=3.9; extra == "dev"
Requires-Dist: pytest>=8.3; extra == "dev"
Requires-Dist: jupyter; extra == "dev"
Requires-Dist: jinja2; extra == "dev"
Provides-Extra: test
Requires-Dist: pytest>=8.3; extra == "test"
Dynamic: license-file
